[{"id": 33204, "title": "Launch Roundup: Kuiper, Starlink, IMAP headline launch manifest", "authors": [{"name": "Justin Davenport", "socials": null}], "url": "https://www.nasaspaceflight.com/2025/09/launch-roundup-092225/", "image_url": "https://www.nasaspaceflight.com/wp-content/uploads/2025/05/julia-streak-1.jpeg", "news_site": "NASASpaceflight", "summary": "A busy slate of launches is planned for the last full week of September, including\u2026\r\nThe post Launch Roundup: Kuiper, Starlink, IMAP headline launch manifest appeared first on NASASpaceFlight.com.", "published_at": "2025-09-22T21:04:34Z", "updated_at": "2025-09-23T07:09:21.670301Z", "featured": false, "launches": [{"launch_id": "9f6d8a5a-f77c-42ff-b377-91628862ae59", "provider": "Launch Library 2"}, {"launch_id": "689d7129-10fa-4df9-b81e-2b8fb926bbaf", "provider": "Launch Library 2"}, {"launch_id": "d260a1bc-c448-4751-8ea6-bc20a3cab779", "provider": "Launch Library 2"}, {"launch_id": "10cb03bb-53df-462f-be12-e8e4b8dcca82", "provider": "Launch Library 2"}, {"launch_id": "018c85ab-533f-4a9c-8b25-a03ca8e824d1", "provider": "Launch Library 2"}, {"launch_id": "c717d2b5-e39c-45a3-9f89-ce73526852eb", "provider": "Launch Library 2"}, {"launch_id": "b563b8fa-9f6c-4883-9a89-9cb5a073864f", "provider": "Launch Library 2"}, {"launch_id": "3dd1e7c0-ceb1-4e28-b6ed-b22c4aec5852", "provider": "Launch Library 2"}, {"launch_id": "ee1f78af-5240-4909-a6f1-54f03de8dd93", "provider": "Launch Library 2"}, {"launch_id": "a99bb1eb-514b-4a93-ac49-5e14f273f250", "provider": "Launch Library 2"}, {"launch_id": "86a178d5-7ea4-4a46-b1d7-801037ea1dfd", "provider": "Launch Library 2"}], "events": []}]