[{"id": 13625, "title": "China\u2019s Landspace appears to be preparing to launch its new methane-fueled rocket", "url": "https://spacenews.com/chinas-landspace-appears-to-be-preparing-to-launch-its-new-methane-fueled-rocket/", "imageUrl": "https://spacenews.com/wp-content/uploads/2020/09/landspace-zhuque-launch-art-sep2020.jpg", "newsSite": "SpaceNews", "summary": "Chinese private company Landspace is working towards a first launch of its new methane-fueled Zhuque-2 rocket with the construction of launch facilities at Jiuquan.", "publishedAt": "2022-01-18T14:42:49.000Z", "updatedAt": "2022-01-18T17:49:05.295Z", "featured": false, "launches": [{"id": "86ea974e-6464-4960-85df-11af88852d57", "provider": "Launch Library 2"}], "events": []}, {"id": 15671, "title": "New launch vehicles set for test flights from China\u2019s Jiuquan spaceport", "url": "https://spacenews.com/new-launch-vehicles-set-for-test-flights-from-chinas-jiuquan-spaceport/", "imageUrl": "https://spacenews.com/wp-content/uploads/2022/07/zhuque-2-Landspace-2022.jpg", "newsSite": "SpaceNews", "summary": "Newly-developed orbital and suborbital launch vehicles are being readied for test flights at the Jiuquan spaceport as China\u2019s efforts to foster a commercial space sector advance.", "publishedAt": "2022-07-06T09:24:58.000Z", "updatedAt": "2022-07-06T18:12:24.519Z", "featured": false, "launches": [{"id": "86ea974e-6464-4960-85df-11af88852d57", "provider": "Launch Library 2"}], "events": []}]